unicorn_binance_rest_api/__init__.c
unicorn_binance_rest_api/__init__.cpython-313-x86_64-linux-gnu.so
unicorn_binance_rest_api/__init__.py
unicorn_binance_rest_api/__init__.pyi
unicorn_binance_rest_api/enums.c
unicorn_binance_rest_api/enums.cpython-313-x86_64-linux-gnu.so
unicorn_binance_rest_api/enums.py
unicorn_binance_rest_api/enums.pyi
unicorn_binance_rest_api/exceptions.c
unicorn_binance_rest_api/exceptions.cpython-313-x86_64-linux-gnu.so
unicorn_binance_rest_api/exceptions.py
unicorn_binance_rest_api/exceptions.pyi
unicorn_binance_rest_api/helpers.c
unicorn_binance_rest_api/helpers.cpython-313-x86_64-linux-gnu.so
unicorn_binance_rest_api/helpers.py
unicorn_binance_rest_api/helpers.pyi
unicorn_binance_rest_api/manager.c
unicorn_binance_rest_api/manager.cpython-313-x86_64-linux-gnu.so
unicorn_binance_rest_api/manager.py
unicorn_binance_rest_api/manager.pyi
unicorn_binance_rest_api-2.8.1.dist-info/METADATA
unicorn_binance_rest_api-2.8.1.dist-info/WHEEL
unicorn_binance_rest_api-2.8.1.dist-info/top_level.txt
unicorn_binance_rest_api-2.8.1.dist-info/RECORD
unicorn_binance_rest_api-2.8.1.dist-info/licenses/LICENSE
