Metadata-Version: 2.1
Name: unicorn-binance-rest-api
Version: 2.8.1
Summary: A Python SDK to use the Binance REST API`s (com+testnet, com-margin+testnet, com-isolated_margin+testnet, com-futures+testnet, us, tr) in a simple, fast, flexible, robust and fully-featured way.
Home-page: https://github.com/oliver-zehentleitner/unicorn-binance-rest-api
Author: Oliver Zehentleitner
License: MIT
Project-URL: Howto, https://github.com/oliver-zehentleitner/unicorn-binance-rest-api#howto
Project-URL: Documentation, https://oliver-zehentleitner.github.io/unicorn-binance-rest-api
Project-URL: Changes, https://oliver-zehentleitner.github.io/unicorn-binance-rest-api/changelog.html
Project-URL: License, https://oliver-zehentleitner.github.io/unicorn-binance-rest-api/license.html
Project-URL: Issue Tracker, https://github.com/oliver-zehentleitner/unicorn-binance-rest-api/issues
Project-URL: Wiki, https://github.com/oliver-zehentleitner/unicorn-binance-rest-api/wiki
Project-URL: Author, https://www.linkedin.com/in/oliver-zehentleitner
Project-URL: Telegram, https://t.me/unicorndevs
Classifier: Development Status :: 5 - Production/Stable
Classifier: Programming Language :: Python :: 3.8
Classifier: Programming Language :: Python :: 3.9
Classifier: Programming Language :: Python :: 3.10
Classifier: Programming Language :: Python :: 3.11
Classifier: Programming Language :: Python :: 3.12
Classifier: Programming Language :: Python :: 3.13
Classifier: Intended Audience :: Developers
Classifier: Intended Audience :: Financial and Insurance Industry
Classifier: Intended Audience :: Information Technology
Classifier: Intended Audience :: Science/Research
Classifier: Operating System :: OS Independent
Classifier: Topic :: Office/Business :: Financial :: Investment
Classifier: Topic :: Software Development :: Libraries :: Python Modules
Requires-Python: >=3.8.0
License-File: LICENSE
Requires-Dist: certifi>=2025.6.15
Requires-Dist: colorama
Requires-Dist: cryptography>=45.0.4
Requires-Dist: dateparser
Requires-Dist: pyOpenSSL
Requires-Dist: requests>=2.32.4
Requires-Dist: service-identity
Requires-Dist: ujson
Requires-Dist: regex
Requires-Dist: PySocks
Requires-Dist: Cython
